eb_adapters/__init__.py
eb_adapters/base.py
eb_adapters/catboost.py
eb_adapters/lightgbm.py
eb_adapters/prophet.py
eb_adapters/statsmodels.py
eb_adapters-0.2.1.dist-info/licenses/LICENSE
eb_adapters-0.2.1.dist-info/METADATA
eb_adapters-0.2.1.dist-info/WHEEL
eb_adapters-0.2.1.dist-info/top_level.txt
eb_adapters-0.2.1.dist-info/RECORD
