Metadata-Version: 2.4
Name: eb-adapters
Version: 0.2.1
Summary: Adapter layer for third-party forecasting libraries in Electric Barometer
License: BSD-3-Clause
Classifier: Development Status :: 3 - Alpha
Classifier: Intended Audience :: Science/Research
Classifier: Intended Audience :: Developers
Classifier: License :: OSI Approved :: BSD License
Classifier: Programming Language :: Python :: 3
Classifier: Programming Language :: Python :: 3.10
Classifier: Programming Language :: Python :: 3.11
Classifier: Programming Language :: Python :: 3.12
Classifier: Programming Language :: Python :: 3.13
Classifier: Operating System :: OS Independent
Classifier: Topic :: Scientific/Engineering
Requires-Python: >=3.10
License-File: LICENSE
Requires-Dist: numpy
Requires-Dist: pandas
Requires-Dist: eb-metrics<0.3,>=0.2
Requires-Dist: eb-evaluation<0.3,>=0.2
Provides-Extra: prophet
Requires-Dist: prophet>=1.1; extra == "prophet"
Provides-Extra: statsmodels
Requires-Dist: statsmodels>=0.14; extra == "statsmodels"
Provides-Extra: catboost
Requires-Dist: catboost>=1.2; extra == "catboost"
Provides-Extra: lightgbm
Requires-Dist: lightgbm>=4.0; extra == "lightgbm"
Provides-Extra: dev
Requires-Dist: pytest; extra == "dev"
Requires-Dist: pytest-cov; extra == "dev"
Requires-Dist: mypy; extra == "dev"
Requires-Dist: ruff; extra == "dev"
Dynamic: license-file
